cpg_pipes/__init__.py
cpg_pipes/_version.py
cpg_pipes/benchmark.py
cpg_pipes/filter_cutoffs.yaml
cpg_pipes/hail_resources.py
cpg_pipes/hailbatch.py
cpg_pipes/pipeline.py
cpg_pipes/resources.py
cpg_pipes/smdb.py
cpg_pipes/utils.py
cpg_pipes-0.2.9.data/scripts/check_pedigree.py
cpg_pipes-0.2.9.dist-info/LICENSE
cpg_pipes-0.2.9.dist-info/METADATA
cpg_pipes-0.2.9.dist-info/WHEEL
cpg_pipes-0.2.9.dist-info/top_level.txt
cpg_pipes-0.2.9.dist-info/RECORD
