Metadata-Version: 2.1
Name: cpg-pipes
Version: 0.2.9
Summary: Hail Batch pipelines for population genomics and rare deseases projects
Home-page: https://github.com/populationgenomics/production-pipelines
License: MIT
Keywords: bioinformatics
Platform: UNKNOWN
Classifier: Environment :: Console
Classifier: Intended Audience :: Science/Research
Classifier: License :: OSI Approved :: GNU General Public License v3 (GPLv3)
Classifier: Natural Language :: English
Classifier: Operating System :: MacOS :: MacOS X
Classifier: Operating System :: POSIX
Classifier: Operating System :: Unix
Classifier: Programming Language :: Python
Classifier: Topic :: Scientific/Engineering
Classifier: Topic :: Scientific/Engineering :: Bio-Informatics
License-File: LICENSE
